{"moduleName":null,"summaries":[{"symbol":{"__symbol":0,"members":[]},"metadata":{"__symbol":1,"members":[]}},{"symbol":{"__symbol":2,"members":[]},"metadata":{"__symbol":3,"members":[]}},{"symbol":{"__symbol":4,"members":[]},"metadata":{"__symbol":5,"members":[]}},{"symbol":{"__symbol":6,"members":[]},"metadata":{"__symbol":7,"members":[]}},{"symbol":{"__symbol":8,"members":[]},"metadata":{"__symbol":9,"members":[]}},{"symbol":{"__symbol":10,"members":[]},"metadata":{"__symbol":11,"members":[]}},{"symbol":{"__symbol":12,"members":[]},"metadata":{"__symbol":13,"members":[]}},{"symbol":{"__symbol":14,"members":[]},"metadata":{"__symbol":15,"members":[]}},{"symbol":{"__symbol":16,"members":[]},"metadata":{"__symbol":17,"members":[]}},{"symbol":{"__symbol":18,"members":[]},"metadata":{"__symbol":19,"members":[]}},{"symbol":{"__symbol":20,"members":[]},"metadata":{"__symbol":21,"members":[]}},{"symbol":{"__symbol":22,"members":[]},"metadata":{"__symbol":23,"members":[]}},{"symbol":{"__symbol":24,"members":[]},"metadata":{"__symbol":25,"members":[]}},{"symbol":{"__symbol":26,"members":[]},"metadata":{"__symbol":27,"members":[]}},{"symbol":{"__symbol":28,"members":[]},"metadata":{"__symbol":29,"members":[]}},{"symbol":{"__symbol":30,"members":[]},"metadata":{"__symbol":31,"members":[]}},{"symbol":{"__symbol":32,"members":[]},"metadata":{"__symbolic":"class"},"type":{"summaryKind":2,"type":{"reference":{"__symbol":32,"members":[]},"diDeps":[],"lifecycleHooks":[]},"entryComponents":[],"providers":[{"provider":{"token":{"identifier":{"reference":{"__symbol":23,"members":[]},"diDeps":[],"lifecycleHooks":[]}},"useClass":{"reference":{"__symbol":23,"members":[]},"diDeps":[],"lifecycleHooks":[]},"useFactory":null,"deps":[],"multi":false},"module":{"reference":{"__symbol":32,"members":[]},"diDeps":[],"lifecycleHooks":[]}}],"modules":[{"reference":{"__symbol":32,"members":[]},"diDeps":[],"lifecycleHooks":[]}],"exportedDirectives":[],"exportedPipes":[]}}],"symbols":[{"__symbol":0,"name":"IQueueConfiguration","filePath":"./index"},{"__symbol":1,"name":"IQueueConfiguration","filePath":"./queue/IQueueConfiguration"},{"__symbol":2,"name":"LimitedSizeQueue","filePath":"./index"},{"__symbol":3,"name":"LimitedSizeQueue","filePath":"./queue/LimitedSizeQueue"},{"__symbol":4,"name":"ILocalStorageLoggerConfiguration","filePath":"./index"},{"__symbol":5,"name":"ILocalStorageLoggerConfiguration","filePath":"./loggers/ILocalStorageLoggerConfiguration"},{"__symbol":6,"name":"LocalStorageLogger","filePath":"./index"},{"__symbol":7,"name":"LocalStorageLogger","filePath":"./loggers/LocalStorageLogger"},{"__symbol":8,"name":"ConsoleLogger","filePath":"./index"},{"__symbol":9,"name":"ConsoleLogger","filePath":"./loggers/ConsoleLogger"},{"__symbol":10,"name":"NullLogger","filePath":"./index"},{"__symbol":11,"name":"NullLogger","filePath":"./loggers/NullLogger"},{"__symbol":12,"name":"DefaultFormatter","filePath":"./index"},{"__symbol":13,"name":"DefaultFormatter","filePath":"./formatters/DefaultFormatter"},{"__symbol":14,"name":"LogLevel","filePath":"./index"},{"__symbol":15,"name":"LogLevel","filePath":"./core/LogLevel"},{"__symbol":16,"name":"ILog","filePath":"./index"},{"__symbol":17,"name":"ILog","filePath":"./ILog"},{"__symbol":18,"name":"GoogleAnalyticsLogger","filePath":"./index"},{"__symbol":19,"name":"GoogleAnalyticsLogger","filePath":"./loggers/GoogleAnalyticsLogger"},{"__symbol":20,"name":"ILogEntry","filePath":"./index"},{"__symbol":21,"name":"ILogEntry","filePath":"./core/ILogEntry"},{"__symbol":22,"name":"Alogy","filePath":"./index"},{"__symbol":23,"name":"Alogy","filePath":"./alogy"},{"__symbol":24,"name":"AlogyLogDestination","filePath":"./index"},{"__symbol":25,"name":"AlogyLogDestination","filePath":"./alogy"},{"__symbol":26,"name":"LogAPI","filePath":"./index"},{"__symbol":27,"name":"LogAPI","filePath":"./alogy"},{"__symbol":28,"name":"Bookkeeper","filePath":"./index"},{"__symbol":29,"name":"Bookkeeper","filePath":"./queue/Bookkeeper"},{"__symbol":30,"name":"Node","filePath":"./index"},{"__symbol":31,"name":"Node","filePath":"./queue/Node"},{"__symbol":32,"name":"AlogyModule","filePath":"./index"}]}